pylibtreesitter/__init__.py
pylibtreesitter/tree_sitter_kit.py
pylibtypes/__init__.py
pylibtypes/folder_based_class_attrs.py
pylibtypes/named_subclass_factory.py
version/__init__.py
version/_version.py
orgecc_pylib-0.1.3.dist-info/LICENSE
orgecc_pylib-0.1.3.dist-info/METADATA
orgecc_pylib-0.1.3.dist-info/WHEEL
orgecc_pylib-0.1.3.dist-info/top_level.txt
orgecc_pylib-0.1.3.dist-info/RECORD
