Metadata-Version: 2.1
Name: orgecc-pylib
Version: 0.1.3
Summary: Misc. helper functions
Author-email: Elifarley <cedarscript@orgecc.com>
License: Apache-2.0
Project-URL: Homepage, https://github.com/elifarley/pylib/blob/main/types
Project-URL: Repository, https://github.com/elifarley/pylib.git
Classifier: Programming Language :: Python :: 3
Classifier: Programming Language :: Python :: 3.8
Classifier: License :: OSI Approved :: Apache Software License
Classifier: Operating System :: OS Independent
Classifier: Intended Audience :: Developers
Classifier: Topic :: Software Development :: Libraries :: Python Modules
Requires-Python: >=3.8
License-File: LICENSE
Provides-Extra: tree-sitter
Requires-Dist: tree-sitter==0.21.3; extra == "tree-sitter"
Provides-Extra: dev
Requires-Dist: pytest>=7.0; extra == "dev"
Requires-Dist: pytest-cov>=4.1; extra == "dev"
Requires-Dist: twine>=6.0.1; extra == "dev"
Requires-Dist: black>=22.0; extra == "dev"
Requires-Dist: isort>=5.0; extra == "dev"
Requires-Dist: flake8>=4.0; extra == "dev"
Requires-Dist: mypy>=0.900; extra == "dev"
Requires-Dist: coverage>=6.0; extra == "dev"
Requires-Dist: tox>=3.24; extra == "dev"
